bpmn_mp/dispatcher.py
bpmn_mp/parsers/__init__.py
bpmn_mp/parsers/base.py
bpmn_mp/parsers/dispatcher_new.py
bpmn_mp/parsers/bpmn_parser/__init__.py
bpmn_mp/parsers/bpmn_parser/detector.py
bpmn_mp/parsers/bpmn_parser/helper.py
bpmn_mp/parsers/bpmn_parser/parser.py
bpmn_mp/parsers/bpmn_parser/plugin.py
bpmn_mp/parsers/native_parser/__init__.py
bpmn_mp/parsers/native_parser/detector.py
bpmn_mp/parsers/native_parser/helper.py
bpmn_mp/parsers/native_parser/parser.py
bpmn_mp/parsers/native_parser/plugin.py
bpmn_mp/parsers/vdx_parser/__init__.py
bpmn_mp/parsers/vdx_parser/detector.py
bpmn_mp/parsers/vdx_parser/helper.py
bpmn_mp/parsers/vdx_parser/parser.py
bpmn_mp/parsers/vdx_parser/plugin.py
bpmn_mp/parsers/xml_parser/__init__.py
bpmn_mp/parsers/xml_parser/detector.py
bpmn_mp/parsers/xml_parser/helper.py
bpmn_mp/parsers/xml_parser/parser.py
bpmn_mp/parsers/xml_parser/plugin.py
bpmn_mp/parsers/xpdl_parser/__init__.py
bpmn_mp/parsers/xpdl_parser/detector.py
bpmn_mp/parsers/xpdl_parser/helper.py
bpmn_mp/parsers/xpdl_parser/parser.py
bpmn_mp/parsers/xpdl_parser/plugin.py
bpmn_mp/repositories/__init__.py
bpmn_mp/repositories/post_repository.py
bpmn_mp/repositories/parsers_repository/__init__.py
bpmn_mp/repositories/parsers_repository/bpmn_repository.py
bpmn_mp/repositories/parsers_repository/native_repository.py
bpmn_mp/repositories/parsers_repository/xml_repository.py
bpmn_mp/repositories/parsers_repository/xpdl_repository.py
bpmn_neo4j/exceptions/base.py
bpmn_neo4j/parsers/json_parser.py
bpmn_neo4j/parsers/parser_factory.py
bpmn_neo4j/transformers/edges.py
bpmn_neo4j/transformers/graph_transformer.py
bpmn_neo4j/transformers/nodes.py
bpmn_neo4j/transformers/pool_lanes.py
bpmn_neo4j/transformers/transform_input_elements.py
bpmn_neo4j/utils/__init__.py
bpmn_neo4j/utils/logger.py
bpmn_neo4j/validators/bpmn_schema.json
bpmn_neo4j/validators/bpmn_semantic_validator.py
bpmn_neo4j/validators/schema_validator.py
bpmn_graph_transformation-0.1.1.dist-info/METADATA
bpmn_graph_transformation-0.1.1.dist-info/WHEEL
bpmn_graph_transformation-0.1.1.dist-info/top_level.txt
bpmn_graph_transformation-0.1.1.dist-info/RECORD
