Metadata-Version: 2.4
Name: bpmn-graph-transformation
Version: 0.1.1
Summary: Library for converting BPMN JSON to Cypher queries for Neo4j
Author-email: business.aji2022@gmail.com, labiim@protonmail.com, 6025241065@student.its.ac.id, lalualdo@gmail.com
License: MIT
Project-URL: Documentation, https://gitlab.iimlab.id/business-process/LIBRARY-BPMN_Graph_Transformation
Project-URL: Source, https://gitlab.iimlab.id/business-process/LIBRARY-BPMN_Graph_Transformation
Project-URL: Homepage, https://gitlab.iimlab.id/business-process/LIBRARY-BPMN_Graph_Transformation
Requires-Python: >=3.8
Requires-Dist: neo4j>=5.19.0
Requires-Dist: dirtyjson>=1.0.8
Requires-Dist: demjson3>=3.0.6
Requires-Dist: jsonschema>=4.0.0
Requires-Dist: requests>=2.31.0
Requires-Dist: networkx>=3.3
Requires-Dist: isort>=5.0.0
Requires-Dist: mypy>=1.9.0
Requires-Dist: mongomock>=4.1.2
Requires-Dist: pymongo==4.5.0
Requires-Dist: jsonschema>=4.0.0
Provides-Extra: dev
Requires-Dist: pytest; extra == "dev"
Requires-Dist: black; extra == "dev"
Requires-Dist: flake8; extra == "dev"
